README.rst
setup.cfg
setup.py
src/global_storage_json_dict/__init__.py
src/global_storage_json_dict.egg-info/PKG-INFO
src/global_storage_json_dict.egg-info/SOURCES.txt
src/global_storage_json_dict.egg-info/dependency_links.txt
src/global_storage_json_dict.egg-info/top_level.txt