Metadata-Version: 2.1
Name: global-storage-json-dict
Version: 1.0.2
Summary: UNKNOWN
Home-page: https://pypi.org/project/aiofiles/global_storage_json_dict
Author: grin-de-vald1
Author-email: grin-de-vald1@ya.ru
License: MIT
Keywords: json storage flask synchron
Platform: UNKNOWN
